noname_backend/__init__.py
noname_backend/cfg/__init__.py
noname_backend/cfg/config_chain.py
noname_backend/cfg/config_loader.py
noname_backend/cfg/env_config.py
noname_backend/db/__init__.py
noname_backend/db/db_loader.py
noname_backend/flask/__init__.py
noname_backend/flask/http_exception.py
noname_backend_common-0.2.0.dist-info/WHEEL
noname_backend_common-0.2.0.dist-info/METADATA
noname_backend_common-0.2.0.dist-info/RECORD
