Metadata-Version: 2.1
Name: noname-backend-common
Version: 0.2.0
Summary: 
Author: andre
Author-email: andre@void.fyi
Requires-Python: >=3.8,<4.0
Classifier: Programming Language :: Python :: 3
Classifier: Programming Language :: Python :: 3.10
Classifier: Programming Language :: Python :: 3.8
Classifier: Programming Language :: Python :: 3.9
Requires-Dist: Flask
Requires-Dist: peewee
Requires-Dist: pysqlite3
